odoo/addons/web_tree_duplicate/README.rst
odoo/addons/web_tree_duplicate/__init__.py
odoo/addons/web_tree_duplicate/__manifest__.py
odoo/addons/web_tree_duplicate/demo/res_users_view.xml
odoo/addons/web_tree_duplicate/i18n/ca.po
odoo/addons/web_tree_duplicate/i18n/es.po
odoo/addons/web_tree_duplicate/i18n/fr.po
odoo/addons/web_tree_duplicate/i18n/pt.po
odoo/addons/web_tree_duplicate/i18n/pt_BR.po
odoo/addons/web_tree_duplicate/i18n/web_tree_duplicate.pot
odoo/addons/web_tree_duplicate/i18n/zh_CN.po
odoo/addons/web_tree_duplicate/readme/CONFIGURE.rst
odoo/addons/web_tree_duplicate/readme/CONTRIBUTORS.rst
odoo/addons/web_tree_duplicate/readme/DESCRIPTION.rst
odoo/addons/web_tree_duplicate/readme/USAGE.rst
odoo/addons/web_tree_duplicate/static/description/icon.png
odoo/addons/web_tree_duplicate/static/description/index.html
odoo/addons/web_tree_duplicate/static/description/screenshot-duplicate.png
odoo/addons/web_tree_duplicate/static/src/js/backend.js
odoo/addons/web_tree_duplicate/templates/assets.xml
odoo12_addon_web_tree_duplicate-12.0.1.0.0.99.dev20.dist-info/METADATA
odoo12_addon_web_tree_duplicate-12.0.1.0.0.99.dev20.dist-info/WHEEL
odoo12_addon_web_tree_duplicate-12.0.1.0.0.99.dev20.dist-info/top_level.txt
odoo12_addon_web_tree_duplicate-12.0.1.0.0.99.dev20.dist-info/RECORD
